escrowai_encrypt/__init__.py
escrowai_encrypt/decryption.py
escrowai_encrypt/encryption.py
escrowai_encrypt/main.py
escrowai_encrypt/utils.py
escrowai_encrypt-0.0.2.dist-info/METADATA
escrowai_encrypt-0.0.2.dist-info/WHEEL
escrowai_encrypt-0.0.2.dist-info/entry_points.txt
escrowai_encrypt-0.0.2.dist-info/top_level.txt
escrowai_encrypt-0.0.2.dist-info/RECORD
