Metadata-Version: 2.4
Name: escrowai-encrypt
Version: 0.0.2
Summary: CLI tool and Python library for encrypting algorithms and datasets with AES-256-GCM for secure computation on EscrowAI
Home-page: https://github.com/BeeKeeperAI/escrowai-encrypt
Author: BeeKeeperAI
Author-email: engineering@beekeeperai.com
License: MIT
Project-URL: Bug Reports, https://github.com/BeeKeeperAI/escrowai-encrypt/issues
Project-URL: Source, https://github.com/BeeKeeperAI/escrowai-encrypt
Project-URL: Documentation, https://github.com/BeeKeeperAI/escrowai-encrypt#readme
Keywords: encryption,aes,gcm,azure,blob-storage,escrowai,algorithm-encryption,dataset-encryption,secure-computation,cryptography
Classifier: Development Status :: 4 - Beta
Classifier: Environment :: Console
Classifier: Intended Audience :: Developers
Classifier: Intended Audience :: Science/Research
Classifier: License :: OSI Approved :: MIT License
Classifier: Operating System :: OS Independent
Classifier: Programming Language :: Python :: 3
Classifier: Programming Language :: Python :: 3.6
Classifier: Programming Language :: Python :: 3.7
Classifier: Programming Language :: Python :: 3.8
Classifier: Programming Language :: Python :: 3.9
Classifier: Programming Language :: Python :: 3.10
Classifier: Programming Language :: Python :: 3.11
Classifier: Programming Language :: Python :: 3.12
Classifier: Programming Language :: Python :: 3.13
Classifier: Topic :: Security :: Cryptography
Classifier: Topic :: Software Development :: Libraries :: Python Modules
Classifier: Topic :: System :: Archiving :: Compression
Requires-Python: >=3.6
Requires-Dist: azure-storage-blob
Requires-Dist: cryptography
Requires-Dist: pyyaml
Dynamic: author
Dynamic: author-email
Dynamic: classifier
Dynamic: description
Dynamic: description-content-type
Dynamic: home-page
Dynamic: keywords
Dynamic: license
Dynamic: project-url
Dynamic: requires-dist
Dynamic: requires-python
Dynamic: summary
